{
  "run_id": "20260313_063721_SVRGOuterLoop",
  "algorithm": "SVRGOuterLoop",
  "started_at": "2026-03-13T06:37:21+00:00",
  "finished_at": "2026-03-13T06:37:22+00:00",
  "success": false,
  "prompt_hashes": {
    "prompts_py": "sha256:a56905669b57679e...",
    "meta_prompts_md": "sha256:5b256051055fc7b2..."
  },
  "events": [
    {
      "id": 1,
      "type": "run_start",
      "algorithm": "SVRGOuterLoop",
      "prompt_hashes": {
        "prompts_py": "sha256:a56905669b57679e...",
        "meta_prompts_md": "sha256:5b256051055fc7b2..."
      },
      "ts": "2026-03-13T06:37:21+00:00"
    },
    {
      "id": 2,
      "type": "run_end",
      "success": false,
      "ts": "2026-03-13T06:37:22+00:00"
    }
  ],
  "phase1_detail": null,
  "phase2_rounds": [],
  "phase3_execution_history": [],
  "phase3_attempt_failures": [],
  "phase4_patch_ops_summary": [],
  "files_modified": [],
  "execution_history": [],
  "attempt_failures": [],
  "agent7_invocations": [],
  "agent7_step_execution_log": [],
  "agent7_plan_revisions": [],
  "agent7_blocked_actions": [],
  "agent7_forced_trigger_count": 0,
  "agent7_force_gate_entries": [],
  "agent7_force_gate_rejections": [],
  "agent7_force_gate_reason_samples": [],
  "git_run_start_sha": "2054c39205652f97b3bc489045af994c4f1bc14f",
  "git_pre_run_dirty": true,
  "git_stash_used": false,
  "git_rollback_applied": true,
  "git_rollback_reason": "run_failed",
  "git_success_restore_ok": true,
  "git_success_restore_error": null,
  "estimated_token_consumption": 0,
  "retry_count": 0,
  "final_files": {
    "Algorithms/SVRGOuterLoop.lean": {
      "hash": "sha256:9303d39da18af9e28869c4694f756fbbd2459cf05f3d12b15d350f5149aba2ee",
      "size_bytes": 10264,
      "content": "import Algorithms.SVRG\nimport Mathlib.Algebra.Field.GeomSum\nimport Lib.Glue.Staging.SVRGOuterLoop\n\n/-!\n# SVRG Outer Loop — Epoch-Level Convergence Analysis\n\nLayer: 2 (concrete algorithm proofs built on inner-loop analysis)\n\nThis file formalizes the macro-level SVRG dynamics across K epochs, where each\nepoch runs m inner steps with a fixed snapshot, then updates the snapshot to\nthe epoch endpoint.\n\n## Mathematical structure\n\n**Update rule (outer loop):**\n$$w_{k+1} = \\text{svrgProcess}(w_k, \\eta, w_k, \\nabla F(w_k), \\xi_{\\text{epoch}}(k), m)$$\n\n**Proof chain:**\n1. Inner epoch contraction (from `svrg_convergence_inner_strongly_convex`)\n2. Variance reduction bound (from `svrg_variance_reduction`)\n3. Gradient norm → distance conversion (from `strongly_convex_gradient_norm_bound`)\n4. Telescope over K epochs → geometric series closed form\n\n## Archetype: B\n\nThe outer loop has a novel two-level structure:\n- **Inner epoch**: Archetype A (reduces to plain SGD via `effectiveSGDSetup`)\n- **Outer loop**: Archetype B (snapshot update creates iterate-dependent variance)\n\nThis requires **dual integrability** per GLUE_TRICKS.md Section 4b.\n-/\n\nopen MeasureTheory ProbabilityTheory\nopen scoped InnerProductSpace\n\n-- ============================================================================\n-- Type parameters (file-level context)\n-- ============================================================================\n\nvariable {E : Type*} [NormedAddCommGroup E] [InnerProductSpace ℝ E] [CompleteSpace E]\n  [MeasurableSpace E] [BorelSpace E] [SecondCountableTopology E]\nvariable {S : Type*} [MeasurableSpace S]\nvariable {Ω : Type*} [MeasurableSpace Ω]\n\n-- ============================================================================\n-- Section 1: SVRG Outer Loop Setup Structure\n-- ============================================================================\n\n/-- SVRG outer-loop setup: extends inner-loop setup with epoch-level sampling.\n\nUsed in: `SVRG outer loop` (Algorithms/SVRGOuterLoop.lean, structure definition) -/\nstructure SVRGOuterSetup\n    (E : Type*) [NormedAddCommGroup E] [InnerProductSpace ℝ E] [CompleteSpace E]\n      [MeasurableSpace E] [BorelSpace E]\n    (S : Type*) [MeasurableSpace S]\n    (Ω : Type*) [MeasurableSpace Ω] where\n  toSVRGSetup : SVRGSetup E S Ω\n  m : ℕ\n  hm_pos : 0 < m\n  -- Epoch-level sampling: ξ_epoch(k, j, ω) for epoch k, inner step j\n  epochStream : ℕ → ℕ → Ω → S\n  h_epoch_meas : ∀ k j, Measurable (epochStream k j)\n  -- Independence across epochs (each epoch's sample stream is independent)\n  h_epoch_indep : ∀ k₁ k₂, k₁ ≠ k₂ →\n    ∀ j₁ j₂, IndepFun (epochStream k₁ j₁) (epochStream k₂ j₂) toSVRGSetup.toSGDSetup.P\n  -- Identical distribution within and across epochs\n  h_epoch_ident : ∀ k j, IdentDistrib (epochStream k j) (toSVRGSetup.toSGDSetup.ξ 0)\n    toSVRGSetup.toSGDSetup.P toSVRGSetup.toSGDSetup.P\n\nnamespace SVRGOuterSetup\n\n/-- Epoch-indexed iterate: `outerProcess k ω` is the snapshot at epoch k.\n\nUsed in: `SVRG outer loop` (Algorithms/SVRGOuterLoop.lean, epoch iterate definition) -/\nnoncomputable def outerProcess (setup : SVRGOuterSetup E S Ω) : ℕ → Ω → E\n  | 0, ω => setup.toSVRGSetup.toSGDSetup.w₀\n  | k + 1, ω =>\n      let w_k := outerProcess setup k ω\n      let gradF_wk := setup.toSVRGSetup.toSGDSetup.gradF w_k\n      setup.toSVRGSetup.svrgProcess w_k gradF_wk setup.m ω\n\nomit [SecondCountableTopology E] in\n@[simp] theorem outerProcess_zero (setup : SVRGOuterSetup E S Ω) :\n    outerProcess setup 0 = fun _ => setup.toSVRGSetup.toSGDSetup.w₀ := rfl\n\nomit [SecondCountableTopology E] in\n@[simp] theorem outerProcess_succ (setup : SVRGOuterSetup E S Ω) (k : ℕ) :\n    outerProcess setup (k + 1) = fun ω =>\n      setup.toSVRGSetup.svrgProcess (outerProcess setup k ω)\n        (setup.toSVRGSetup.toSGDSetup.gradF (outerProcess setup k ω))\n        setup.m ω := rfl\n\n-- ============================================================================\n-- Section 2: Measurability and Independence Infrastructure\n-- ============================================================================\n\n/-- Measurability of epoch iterates.\n\nUsed in: `SVRG outer loop` (Algorithms/SVRGOuterLoop.lean, Step 4 — measurability bridge) -/\ntheorem outerProcess_measurable\n    (setup : SVRGOuterSetup E S Ω)\n    (hgL : Measurable (Function.uncurry setup.toSVRGSetup.toSGDSetup.gradL))\n    (hgF : Measurable setup.toSVRGSetup.toSGDSetup.gradF) (k : ℕ) :\n    Measurable (outerProcess setup k) := by\n  induction k with\n  | zero => exact measurable_const\n  | succ k ih =>\n      have h_wk_meas : Measurable (outerProcess setup k) := ih\n      have h_gradF_wk_meas : Measurable (fun ω => setup.toSVRGSetup.toSGDSetup.gradF (outerProcess setup k ω)) :=\n        hgF.comp h_wk_meas\n      -- Apply staging lemma: svrgProcess with random snapshot (w_k, gradF w_k)\n      simpa [SVRGOuterSetup.outerProcess, SVRGSetup.svrgProcess] using\n        svrgProcess_measurable_random_snapshot setup.toSVRGSetup\n          (outerProcess setup k) (fun ω => setup.toSVRGSetup.toSGDSetup.gradF (outerProcess setup k ω))\n          h_wk_meas h_gradF_wk_meas hgL setup.m\n\n/-- Independence of epoch k iterate from epoch k samples.\n\nUsed in: `SVRG outer loop` (Algorithms/SVRGOuterLoop.lean, Step 4 — independence bridge) -/\ntheorem outerProcess_indepFun_epoch\n    (setup : SVRGOuterSetup E S Ω)\n    (hgL : Measurable (Function.uncurry setup.toSVRGSetup.toSGDSetup.gradL))\n    (hgF : Measurable setup.toSVRGSetup.toSGDSetup.gradF) (k : ℕ) :\n    ∀ j, IndepFun (outerProcess setup k) (setup.epochStream k j) setup.toSVRGSetup.toSGDSetup.P := by\n  intro j\n  sorry\n\n-- ============================================================================\n-- Section 3: Epoch Contraction Factor\n-- ============================================================================\n\n/-- Epoch contraction factor: ρ = (1-ημ)^m + η·(variance terms)/μ.\n\nUsed in: `SVRG outer loop` (Algorithms/SVRGOuterLoop.lean, contraction factor definition) -/\nnoncomputable def epochContractionFactor (η μ : ℝ) (L : NNReal) (m : ℕ) : ℝ :=\n  (1 - η * μ) ^ m + η * (4 * (L : ℝ) ^ 2 / μ + 2 * (L : ℝ) ^ 2) / μ\n\n-- ============================================================================\n-- Section 4: Main Outer-Loop Convergence Theorem\n-- ============================================================================\n\n/-- SVRG outer-loop convergence: epoch-to-epoch contraction telescoped over K epochs.\n\nUsed in: `SVRG outer loop` (Algorithms/SVRGOuterLoop.lean, Step 6 — main convergence theorem) -/\ntheorem svrg_outer_convergence\n    (setup : SVRGOuterSetup E S Ω) (f : E → ℝ) {L : NNReal} {μ σ η : ℝ} (wStar : E)\n    (hgrad : IsGradientOf f setup.toSVRGSetup.toSGDSetup.gradF)\n    (hsmooth : IsLSmooth setup.toSVRGSetup.toSGDSetup.gradF L)\n    (hsc : StrongConvexOn Set.univ μ f)\n    (hvar : HasBoundedVariance setup.toSVRGSetup.toSGDSetup.gradL setup.toSVRGSetup.sampleDist σ)\n    (hunb : IsUnbiased setup.toSVRGSetup.toSGDSetup.gradL setup.toSVRGSetup.toSGDSetup.gradF setup.toSVRGSetup.sampleDist)\n    (hmin : IsMinimizer f wStar)\n    (h_sample_prob : IsProbabilityMeasure setup.toSVRGSetup.sampleDist)\n    (hμ_pos : 0 < μ) (hη_pos : 0 < η) (hη_L : η ≤ 1 / (2 * (L : ℝ)))\n    (hημ : η * μ < 1)\n    (K : ℕ) (hK_pos : 0 < K)\n    (hgL : Measurable (Function.uncurry setup.toSVRGSetup.toSGDSetup.gradL))\n    (hgF : Measurable setup.toSVRGSetup.toSGDSetup.gradF)\n    (h_intL : ∀ w, Integrable (setup.toSVRGSetup.toSGDSetup.gradL w) setup.toSVRGSetup.sampleDist)\n    (h_int_epoch_end : ∀ k, Integrable (fun ω => ‖outerProcess setup k ω - wStar‖ ^ 2)\n      setup.toSVRGSetup.toSGDSetup.P)\n    (h_int_snapshot : ∀ k, Integrable (fun ω =>\n      ‖setup.toSVRGSetup.svrgProcess (outerProcess setup k ω)\n        (setup.toSVRGSetup.toSGDSetup.gradF (outerProcess setup k ω))\n        setup.m ω - wStar‖ ^ 2) setup.toSVRGSetup.toSGDSetup.P) :\n    ∫ ω, ‖outerProcess setup K ω - wStar‖ ^ 2 ∂setup.toSVRGSetup.toSGDSetup.P ≤\n      (epochContractionFactor η μ L setup.m) ^ K * ‖setup.toSVRGSetup.toSGDSetup.w₀ - wStar‖ ^ 2 := by\n  haveI := setup.toSVRGSetup.toSGDSetup.hP\n  set ρ := epochContractionFactor η μ L setup.m with hρ_def\n  \n  have h_epoch_contract : ∀ k < K,\n      ∫ ω, ‖outerProcess setup (k + 1) ω - wStar‖ ^ 2 ∂setup.toSVRGSetup.toSGDSetup.P ≤\n        ρ * ∫ ω, ‖outerProcess setup k ω - wStar‖ ^ 2 ∂setup.toSVRGSetup.toSGDSetup.P := by\n    intro k hk\n    sorry\n  \n  have h_telescope :\n      ∫ ω, ‖outerProcess setup K ω - wStar‖ ^ 2 ∂setup.toSVRGSetup.toSGDSetup.P ≤\n        ρ ^ K * ‖setup.toSVRGSetup.toSGDSetup.w₀ - wStar‖ ^ 2 := by\n    induction K with\n    | zero =>\n        simp only [outerProcess_zero setup, pow_zero, one_mul]\n        rw [integral_const, smul_eq_mul, probReal_univ, one_mul]\n    | succ K ih =>\n        have h_contract := h_epoch_contract K (Nat.lt_succ_self K)\n        have hρ_nonneg : 0 ≤ ρ := by\n          rw [hρ_def, epochContractionFactor]\n          -- (1 - η*μ)^m ≥ 0 since 0 ≤ 1 - η*μ (from hημ : η*μ < 1)\n          have h1 : 0 ≤ (1 - η * μ) ^ m := pow_nonneg (sub_nonneg.mpr hημ.le) _\n          -- η*(4*L^2/μ + 2*L^2)/μ ≥ 0 since η > 0, L^2 ≥ 0, μ > 0\n          have h2 : 0 ≤ η * (4 * (L : ℝ) ^ 2 / μ + 2 * (L : ℝ) ^ 2) / μ := by\n            apply div_nonneg\n            · apply mul_nonneg hη_pos.le\n              apply add_nonneg\n              · apply div_nonneg\n                · nlinarith [sq_nonneg (L : ℝ)]\n                · exact hμ_pos.le\n              · nlinarith [sq_nonneg (L : ℝ)]\n            · exact hμ_pos.le\n          linarith\n        calc ∫ ω, ‖outerProcess setup (K + 1) ω - wStar‖ ^ 2 ∂setup.toSVRGSetup.toSGDSetup.P\n            ≤ ρ * ∫ ω, ‖outerProcess setup K ω - wStar‖ ^ 2 ∂setup.toSVRGSetup.toSGDSetup.P := h_contract\n          _ ≤ ρ * (ρ ^ K * ‖setup.toSVRGSetup.toSGDSetup.w₀ - wStar‖ ^ 2) := by\n              exact mul_le_mul_of_nonneg_left ih hρ_nonneg\n          _ = ρ ^ (K + 1) * ‖setup.toSVRGSetup.toSGDSetup.w₀ - wStar‖ ^ 2 := by\n              rw [pow_succ]\n  \n  exact h_telescope\n\nend SVRGOuterSetup\n"
    }
  }
}